instanovo/__init__.py
instanovo/cli.py
instanovo/constants.py
instanovo/models.json
instanovo/types.py
instanovo/common/__init__.py
instanovo/common/dataset.py
instanovo/common/predictor.py
instanovo/common/scheduler.py
instanovo/common/trainer.py
instanovo/common/utils.py
instanovo/configs/instanovo.yaml
instanovo/configs/instanovo_unit_test.yaml
instanovo/configs/instanovoplus.yaml
instanovo/configs/instanovoplus_distill.yaml
instanovo/configs/instanovoplus_unit_test.yaml
instanovo/configs/accelerate/aichor.yaml
instanovo/configs/accelerate/local.yaml
instanovo/configs/dataset/acpt.yaml
instanovo/configs/dataset/default.yaml
instanovo/configs/dataset/massivekb.yaml
instanovo/configs/dataset/phospho.yaml
instanovo/configs/dataset/unit_test.yaml
instanovo/configs/finetune/default.yaml
instanovo/configs/inference/default.yaml
instanovo/configs/inference/instanovo-p.yaml
instanovo/configs/inference/instanovo_with_refinement.yaml
instanovo/configs/inference/instanovoplus.yaml
instanovo/configs/inference/instanovoplus_pipeline.yaml
instanovo/configs/inference/instanovoplus_unit_test.yaml
instanovo/configs/inference/pipeline.yaml
instanovo/configs/inference/pipeline_unit_test.yaml
instanovo/configs/inference/unit_test.yaml
instanovo/configs/model/instanovo_8M.yaml
instanovo/configs/model/instanovo_base.yaml
instanovo/configs/model/instanovo_unit_test.yaml
instanovo/configs/model/instanovoplus_base.yaml
instanovo/configs/model/instanovoplus_small.yaml
instanovo/configs/model/instanovoplus_unit_test.yaml
instanovo/configs/residues/default.yaml
instanovo/configs/residues/pride_extended.yaml
instanovo/configs/residues/unit_test.yaml
instanovo/diffusion/__init__.py
instanovo/diffusion/cli.py
instanovo/diffusion/data.py
instanovo/diffusion/layers.py
instanovo/diffusion/model.py
instanovo/diffusion/multinomial_diffusion.py
instanovo/diffusion/predict.py
instanovo/diffusion/train.py
instanovo/inference/__init__.py
instanovo/inference/beam_search.py
instanovo-1.2.2.dist-info/licenses/LICENSE.md
instanovo-1.2.2.dist-info/METADATA
instanovo-1.2.2.dist-info/WHEEL
instanovo-1.2.2.dist-info/entry_points.txt
instanovo-1.2.2.dist-info/top_level.txt
instanovo-1.2.2.dist-info/RECORD
