Metadata-Version: 2.4
Name: instanovo
Version: 1.2.2
Summary: InstaNovo enables diffusion-powered de novo peptide sequencing in large scale proteomics experiments
Author-email: Kevin Michael Eloff <k.eloff@instadeep.com>, Jeroen Van Goey <j.vangoey@instadeep.com>, Amandla Mabona <a.mabona@instadeep.com>, Rachel Catzel <r.catzel@instadeep.com>
License-Expression: Apache-2.0
Project-URL: Homepage, https://github.com/instadeepai/InstaNovo
Project-URL: Issues, https://github.com/instadeepai/InstaNovo/issues
Project-URL: documentation, https://instadeepai.github.io/InstaNovo/
Keywords: mass spectrometry,bioinformatics,machine learning,deep learning,transformer,de novo peptide sequencing
Classifier: Programming Language :: Python :: 3
Classifier: Operating System :: OS Independent
Requires-Python: <3.14,>=3.10
License-File: LICENSE.md
Requires-Dist: accelerate>=1.6.0
Requires-Dist: datasets>=3.5.0
Requires-Dist: gitpython>=3.1.44
Requires-Dist: hydra-core>=1.3.2
Requires-Dist: jaxtyping>=0.2.34
Requires-Dist: jiwer>=3.0.5
Requires-Dist: matchms>=0.28.1
Requires-Dist: neptune>=1.13.0
Requires-Dist: numpy>=2.0.2
Requires-Dist: omegaconf>=2.3.0
Requires-Dist: pandas>=2.2.3
Requires-Dist: polars>=1.12.0
Requires-Dist: pubchempy>=1.0.4
Requires-Dist: pyteomics>=4.7.5
Requires-Dist: python-dotenv>=1.0.1
Requires-Dist: pyyaml>=6.0.2
Requires-Dist: requests>=2.32.3
Requires-Dist: s3fs>=2024.12.0
Requires-Dist: scikit-learn>=1.5.2
Requires-Dist: signalrcore
Requires-Dist: spectrum-utils>=0.4.2
Requires-Dist: tensorboard>=2.18.0
Requires-Dist: tqdm>=4.67.0
Requires-Dist: transfusion-asr>=0.1.0
Requires-Dist: typer>=0.15.1
Provides-Extra: cpu
Requires-Dist: torch<2.8,>2.5; sys_platform == "darwin" and extra == "cpu"
Requires-Dist: torch<2.9,>2.5; (sys_platform == "linux" or sys_platform == "win32") and extra == "cpu"
Provides-Extra: cu124
Requires-Dist: torch<2.5,>=2.4.1; extra == "cu124"
Provides-Extra: cu126
Requires-Dist: torch<2.8,>=2.5; sys_platform == "darwin" and extra == "cu126"
Requires-Dist: torch<2.9,>=2.5; (sys_platform == "linux" or sys_platform == "win32") and extra == "cu126"
Dynamic: license-file
